fox_orm/__init__.py
fox_orm/controller.py
fox_orm/exceptions.py
fox_orm/fields.py
fox_orm/internal/__init__.py
fox_orm/internal/columns.py
fox_orm/internal/const.py
fox_orm/internal/table.py
fox_orm/internal/utils.py
fox_orm/model.py
fox_orm/relations.py
fox_orm-0.3.6.1.dist-info/LICENSE
fox_orm-0.3.6.1.dist-info/WHEEL
fox_orm-0.3.6.1.dist-info/METADATA
fox_orm-0.3.6.1.dist-info/RECORD
